pyhamtools/__init__.py
pyhamtools/callinfo.py
pyhamtools/callsign_exceptions.py
pyhamtools/consts.py
pyhamtools/countryfilemapping.json
pyhamtools/dxcluster.py
pyhamtools/exceptions.py
pyhamtools/frequency.py
pyhamtools/locator.py
pyhamtools/logparser.py
pyhamtools/lookuplib.py
pyhamtools/qsl.py
pyhamtools/utils.py
pyhamtools/version.py
pyhamtools-0.7.8.dist-info/LICENSE
pyhamtools-0.7.8.dist-info/METADATA
pyhamtools-0.7.8.dist-info/WHEEL
pyhamtools-0.7.8.dist-info/top_level.txt
pyhamtools-0.7.8.dist-info/RECORD
