Metadata-Version: 2.1
Name: pyhamtools
Version: 0.7.8
Summary: Collection of Tools for Amateur Radio developers
Home-page: http://github.com/dh1tw/pyhamtools
Author: Tobias Wellnitz, DH1TW
Author-email: Tobias@dh1tw.de
License: UNKNOWN
Platform: UNKNOWN
License-File: LICENSE
Requires-Dist: pytz (>=2019.1)
Requires-Dist: requests (>=2.21.0)
Requires-Dist: pyephem (>=3.7.6.0)
Requires-Dist: beautifulsoup4 (>=4.7.1)
Requires-Dist: future (>=0.17.1)
Requires-Dist: redis (>=2.10.6)
